{
  "pokemons": [{
      "number": 1,
      "name": "Bulbizarre"
    },
    {
      "number": 2,
      "name": "Herbizarre"
    },
    {
      "number": 3,
      "name": "Florizarre"
    },
    {
      "number": 4,
      "name": "Salamèche"
    },
    {
      "number": 5,
      "name": "Reptincel"
    },
    {
      "number": 6,
      "name": "Dracaufeu"
    },
    {
      "number": 7,
      "name": "Carapuce"
    },
    {
      "number": 8,
      "name": "Carabaffe"
    },
    {
      "number": 9,
      "name": "Tortank"
    },
    {
      "number": 10,
      "name": "Chenipan"
    },
    {
      "number": 11,
      "name": "Chrysacier"
    },
    {
      "number": 12,
      "name": "Papilusion"
    },
    {
      "number": 13,
      "name": "Aspicot"
    },
    {
      "number": 14,
      "name": "Coconfort"
    },
    {
      "number": 15,
      "name": "Dardargnan"
    },
    {
      "number": 16,
      "name": "Roucool"
    },
    {
      "number": 17,
      "name": "Roucoups"
    },
    {
      "number": 18,
      "name": "Roucarnage"
    },
    {
      "number": 19,
      "name": "Rattata"
    },
    {
      "number": 20,
      "name": "Rattatac"
    },
    {
      "number": 21,
      "name": "Piafabec"
    },
    {
      "number": 22,
      "name": "Rapasdepic"
    },
    {
      "number": 23,
      "name": "Abo"
    },
    {
      "number": 24,
      "name": "Arbok"
    },
    {
      "number": 25,
      "name": "Pikachu"
    },
    {
      "number": 26,
      "name": "Raichu"
    },
    {
      "number": 27,
      "name": "Sabelette"
    },
    {
      "number": 28,
      "name": "Sablaireau"
    },
    {
      "number": 29,
      "name": "Nidoran♀"
    },
    {
      "number": 30,
      "name": "Nidorina"
    },
    {
      "number": 31,
      "name": "Nidoqueen"
    },
    {
      "number": 32,
      "name": "Nidoran♂"
    },
    {
      "number": 33,
      "name": "Nidorino"
    },
    {
      "number": 34,
      "name": "Nidoking"
    },
    {
      "number": 35,
      "name": "Mélofée"
    },
    {
      "number": 36,
      "name": "Mélodelfe"
    },
    {
      "number": 37,
      "name": "Goupix"
    },
    {
      "number": 38,
      "name": "Feunard"
    },
    {
      "number": 39,
      "name": "Rondoudou"
    },
    {
      "number": 40,
      "name": "Grodoudou"
    },
    {
      "number": 41,
      "name": "Nosferapti"
    },
    {
      "number": 42,
      "name": "Nosferalto"
    },
    {
      "number": 43,
      "name": "Mystherbe"
    },
    {
      "number": 44,
      "name": "Ortide"
    },
    {
      "number": 45,
      "name": "Rafflesia"
    },
    {
      "number": 46,
      "name": "Paras"
    },
    {
      "number": 47,
      "name": "Parasect"
    },
    {
      "number": 48,
      "name": "Mimitoss"
    },
    {
      "number": 49,
      "name": "Aéromite"
    },
    {
      "number": 50,
      "name": "Taupiqueur"
    },
    {
      "number": 51,
      "name": "Triopikeur"
    },
    {
      "number": 52,
      "name": "Miaouss"
    },
    {
      "number": 53,
      "name": "Persian"
    },
    {
      "number": 54,
      "name": "Psykokwak"
    },
    {
      "number": 55,
      "name": "Akwakwak"
    },
    {
      "number": 56,
      "name": "Férosinge"
    },
    {
      "number": 57,
      "name": "Colossinge"
    },
    {
      "number": 58,
      "name": "Caninos"
    },
    {
      "number": 59,
      "name": "Arcanin"
    },
    {
      "number": 60,
      "name": "Ptitard"
    },
    {
      "number": 61,
      "name": "Têtarte"
    },
    {
      "number": 62,
      "name": "Tartard"
    },
    {
      "number": 63,
      "name": "Abra"
    },
    {
      "number": 64,
      "name": "Kadabra"
    },
    {
      "number": 65,
      "name": "Alakazam"
    },
    {
      "number": 66,
      "name": "Machoc"
    },
    {
      "number": 67,
      "name": "Machopeur"
    },
    {
      "number": 68,
      "name": "Mackogneur"
    },
    {
      "number": 69,
      "name": "Chétiflor"
    },
    {
      "number": 70,
      "name": "Boustiflor"
    },
    {
      "number": 71,
      "name": "Empiflor"
    },
    {
      "number": 72,
      "name": "Tentacool"
    },
    {
      "number": 73,
      "name": "Tentacruel"
    },
    {
      "number": 74,
      "name": "Racaillou"
    },
    {
      "number": 75,
      "name": "Gravalanch"
    },
    {
      "number": 76,
      "name": "Grolem"
    },
    {
      "number": 77,
      "name": "Ponyta"
    },
    {
      "number": 78,
      "name": "Galopa"
    },
    {
      "number": 79,
      "name": "Ramoloss"
    },
    {
      "number": 80,
      "name": "Flagadoss"
    },
    {
      "number": 81,
      "name": "Magnéti"
    },
    {
      "number": 82,
      "name": "Magnéton"
    },
    {
      "number": 83,
      "name": "Canarticho"
    },
    {
      "number": 84,
      "name": "Doduo"
    },
    {
      "number": 85,
      "name": "Dodrio"
    },
    {
      "number": 86,
      "name": "Otaria"
    },
    {
      "number": 87,
      "name": "Lamantine"
    },
    {
      "number": 88,
      "name": "Tadmorv"
    },
    {
      "number": 89,
      "name": "Grotadmorv"
    },
    {
      "number": 90,
      "name": "Kokiyas"
    },
    {
      "number": 91,
      "name": "Crustabri"
    },
    {
      "number": 92,
      "name": "Fantominus"
    },
    {
      "number": 93,
      "name": "Spectrum"
    },
    {
      "number": 94,
      "name": "Ectoplasma"
    },
    {
      "number": 95,
      "name": "Onix"
    },
    {
      "number": 96,
      "name": "Soporifik"
    },
    {
      "number": 97,
      "name": "Hypnomade"
    },
    {
      "number": 98,
      "name": "Krabby"
    },
    {
      "number": 99,
      "name": "Krabboss"
    },
    {
      "number": 100,
      "name": "Voltorbe"
    },
    {
      "number": 101,
      "name": "Électrode"
    },
    {
      "number": 102,
      "name": "Nœunœuf"
    },
    {
      "number": 103,
      "name": "Noadkoko"
    },
    {
      "number": 104,
      "name": "Osselait"
    },
    {
      "number": 105,
      "name": "Ossatueur"
    },
    {
      "number": 106,
      "name": "Kicklee"
    },
    {
      "number": 107,
      "name": "Tygnon"
    },
    {
      "number": 108,
      "name": "Excelangue"
    },
    {
      "number": 109,
      "name": "Smogo"
    },
    {
      "number": 110,
      "name": "Smogogo"
    },
    {
      "number": 111,
      "name": "Rhinocorne"
    },
    {
      "number": 112,
      "name": "Rhinoféros"
    },
    {
      "number": 113,
      "name": "Leveinard"
    },
    {
      "number": 114,
      "name": "Saquedeneu"
    },
    {
      "number": 115,
      "name": "Kangourex"
    },
    {
      "number": 116,
      "name": "Hypotrempe"
    },
    {
      "number": 117,
      "name": "Hypocéan"
    },
    {
      "number": 118,
      "name": "Poissirène"
    },
    {
      "number": 119,
      "name": "Poissoroy"
    },
    {
      "number": 120,
      "name": "Stari"
    },
    {
      "number": 121,
      "name": "Staross"
    },
    {
      "number": 122,
      "name": "M. Mime"
    },
    {
      "number": 123,
      "name": "Insécateur"
    },
    {
      "number": 124,
      "name": "Lippoutou"
    },
    {
      "number": 125,
      "name": "Élektek"
    },
    {
      "number": 126,
      "name": "Magmar"
    },
    {
      "number": 127,
      "name": "Scarabrute"
    },
    {
      "number": 128,
      "name": "Tauros"
    },
    {
      "number": 129,
      "name": "Magicarpe"
    },
    {
      "number": 130,
      "name": "Léviator"
    },
    {
      "number": 131,
      "name": "Lokhlass"
    },
    {
      "number": 132,
      "name": "Métamorph"
    },
    {
      "number": 133,
      "name": "Évoli"
    },
    {
      "number": 134,
      "name": "Aquali"
    },
    {
      "number": 135,
      "name": "Voltali"
    },
    {
      "number": 136,
      "name": "Pyroli"
    },
    {
      "number": 137,
      "name": "Porygon"
    },
    {
      "number": 138,
      "name": "Amonita"
    },
    {
      "number": 139,
      "name": "Amonistar"
    },
    {
      "number": 140,
      "name": "Kabuto"
    },
    {
      "number": 141,
      "name": "Kabutops"
    },
    {
      "number": 142,
      "name": "Ptéra"
    },
    {
      "number": 143,
      "name": "Ronflex"
    },
    {
      "number": 144,
      "name": "Artikodin"
    },
    {
      "number": 145,
      "name": "Électhor"
    },
    {
      "number": 146,
      "name": "Sulfura"
    },
    {
      "number": 147,
      "name": "Minidraco"
    },
    {
      "number": 148,
      "name": "Draco"
    },
    {
      "number": 149,
      "name": "Dracolosse"
    },
    {
      "number": 150,
      "name": "Mewtwo"
    },
    {
      "number": 151,
      "name": "Mew"
    },
    {
      "number": 152,
      "name": "Germignon"
    },
    {
      "number": 153,
      "name": "Macronium"
    },
    {
      "number": 154,
      "name": "Méganium"
    },
    {
      "number": 155,
      "name": "Héricendre"
    },
    {
      "number": 156,
      "name": "Feurisson"
    },
    {
      "number": 157,
      "name": "Typhlosion"
    },
    {
      "number": 158,
      "name": "Kaiminus"
    },
    {
      "number": 159,
      "name": "Crocrodil"
    },
    {
      "number": 160,
      "name": "Aligatueur"
    },
    {
      "number": 161,
      "name": "Fouinette"
    },
    {
      "number": 162,
      "name": "Fouinar"
    },
    {
      "number": 163,
      "name": "Hoothoot"
    },
    {
      "number": 164,
      "name": "Noarfang"
    },
    {
      "number": 165,
      "name": "Coxy"
    },
    {
      "number": 166,
      "name": "Coxyclaque"
    },
    {
      "number": 167,
      "name": "Mimigal"
    },
    {
      "number": 168,
      "name": "Migalos"
    },
    {
      "number": 169,
      "name": "Nostenfer"
    },
    {
      "number": 170,
      "name": "Loupio"
    },
    {
      "number": 171,
      "name": "Lanturn"
    },
    {
      "number": 172,
      "name": "Pichu"
    },
    {
      "number": 173,
      "name": "Mélo"
    },
    {
      "number": 174,
      "name": "Toudoudou"
    },
    {
      "number": 175,
      "name": "Togepi"
    },
    {
      "number": 176,
      "name": "Togetic"
    },
    {
      "number": 177,
      "name": "Natu"
    },
    {
      "number": 178,
      "name": "Xatu"
    },
    {
      "number": 179,
      "name": "Wattouat"
    },
    {
      "number": 180,
      "name": "Lainergie"
    },
    {
      "number": 181,
      "name": "Pharamp"
    },
    {
      "number": 182,
      "name": "Joliflor"
    },
    {
      "number": 183,
      "name": "Marill"
    },
    {
      "number": 184,
      "name": "Azumarill"
    },
    {
      "number": 185,
      "name": "Simularbre"
    },
    {
      "number": 186,
      "name": "Tarpaud"
    },
    {
      "number": 187,
      "name": "Granivol"
    },
    {
      "number": 188,
      "name": "Floravol"
    },
    {
      "number": 189,
      "name": "Cotovol"
    },
    {
      "number": 190,
      "name": "Capumain"
    },
    {
      "number": 191,
      "name": "Tournegrin"
    },
    {
      "number": 192,
      "name": "Héliatronc"
    },
    {
      "number": 193,
      "name": "Yanma"
    },
    {
      "number": 194,
      "name": "Axoloto"
    },
    {
      "number": 195,
      "name": "Maraiste"
    },
    {
      "number": 196,
      "name": "Mentali"
    },
    {
      "number": 197,
      "name": "Noctali"
    },
    {
      "number": 198,
      "name": "Cornèbre"
    },
    {
      "number": 199,
      "name": "Roigada"
    },
    {
      "number": 200,
      "name": "Feuforêve"
    },
    {
      "number": 201,
      "name": "Zarbi"
    },
    {
      "number": 202,
      "name": "Qulbutoké"
    },
    {
      "number": 203,
      "name": "Girafarig"
    },
    {
      "number": 204,
      "name": "Pomdepik"
    },
    {
      "number": 205,
      "name": "Foretress"
    },
    {
      "number": 206,
      "name": "Insolourdo"
    },
    {
      "number": 207,
      "name": "Scorplane"
    },
    {
      "number": 208,
      "name": "Steelix"
    },
    {
      "number": 209,
      "name": "Snubbull"
    },
    {
      "number": 210,
      "name": "Granbull"
    },
    {
      "number": 211,
      "name": "Qwilfish"
    },
    {
      "number": 212,
      "name": "Cizayox"
    },
    {
      "number": 213,
      "name": "Caratroc"
    },
    {
      "number": 214,
      "name": "Scarhino"
    },
    {
      "number": 215,
      "name": "Farfuret"
    },
    {
      "number": 216,
      "name": "Teddiursa"
    },
    {
      "number": 217,
      "name": "Ursaring"
    },
    {
      "number": 218,
      "name": "Limagma"
    },
    {
      "number": 219,
      "name": "Volcaropod"
    },
    {
      "number": 220,
      "name": "Marcacrin"
    },
    {
      "number": 221,
      "name": "Cochignon"
    },
    {
      "number": 222,
      "name": "Corayon"
    },
    {
      "number": 223,
      "name": "Rémoraid"
    },
    {
      "number": 224,
      "name": "Octillery"
    },
    {
      "number": 225,
      "name": "Cadoizo"
    },
    {
      "number": 226,
      "name": "Démanta"
    },
    {
      "number": 227,
      "name": "Airmure"
    },
    {
      "number": 228,
      "name": "Malosse"
    },
    {
      "number": 229,
      "name": "Démolosse"
    },
    {
      "number": 230,
      "name": "Hyporoi"
    },
    {
      "number": 231,
      "name": "Phanpy"
    },
    {
      "number": 232,
      "name": "Donphan"
    },
    {
      "number": 233,
      "name": "Porygon2"
    },
    {
      "number": 234,
      "name": "Cerfrousse"
    },
    {
      "number": 235,
      "name": "Queulorior"
    },
    {
      "number": 236,
      "name": "Debugant"
    },
    {
      "number": 237,
      "name": "Kapoera"
    },
    {
      "number": 238,
      "name": "Lippouti"
    },
    {
      "number": 239,
      "name": "Élekid"
    },
    {
      "number": 240,
      "name": "Magby"
    },
    {
      "number": 241,
      "name": "Écrémeuh"
    },
    {
      "number": 242,
      "name": "Leuphorie"
    },
    {
      "number": 243,
      "name": "Raikou"
    },
    {
      "number": 244,
      "name": "Entei"
    },
    {
      "number": 245,
      "name": "Suicune"
    },
    {
      "number": 246,
      "name": "Embrylex"
    },
    {
      "number": 247,
      "name": "Ymphect"
    },
    {
      "number": 248,
      "name": "Tyranocif"
    },
    {
      "number": 249,
      "name": "Lugia"
    },
    {
      "number": 250,
      "name": "Ho-Oh"
    },
    {
      "number": 251,
      "name": "Celebi"
    },
    {
      "number": 252,
      "name": "Arcko"
    },
    {
      "number": 253,
      "name": "Massko"
    },
    {
      "number": 254,
      "name": "Jungko"
    },
    {
      "number": 255,
      "name": "Poussifeu"
    },
    {
      "number": 256,
      "name": "Galifeu"
    },
    {
      "number": 257,
      "name": "Braségali"
    },
    {
      "number": 258,
      "name": "Gobou"
    },
    {
      "number": 259,
      "name": "Flobio"
    },
    {
      "number": 260,
      "name": "Laggron"
    },
    {
      "number": 261,
      "name": "Medhyèna"
    },
    {
      "number": 262,
      "name": "Grahyèna"
    },
    {
      "number": 263,
      "name": "Zigzaton"
    },
    {
      "number": 264,
      "name": "Linéon"
    },
    {
      "number": 265,
      "name": "Chenipotte"
    },
    {
      "number": 266,
      "name": "Armulys"
    },
    {
      "number": 267,
      "name": "Charmillon"
    },
    {
      "number": 268,
      "name": "Blindalys"
    },
    {
      "number": 269,
      "name": "Papinox"
    },
    {
      "number": 270,
      "name": "Nénupiot"
    },
    {
      "number": 271,
      "name": "Lombre"
    },
    {
      "number": 272,
      "name": "Ludicolo"
    },
    {
      "number": 273,
      "name": "Grainipiot"
    },
    {
      "number": 274,
      "name": "Pifeuil"
    },
    {
      "number": 275,
      "name": "Tengalice"
    },
    {
      "number": 276,
      "name": "Nirondelle"
    },
    {
      "number": 277,
      "name": "Hélédelle"
    },
    {
      "number": 278,
      "name": "Goélise"
    },
    {
      "number": 279,
      "name": "Bekipan"
    },
    {
      "number": 280,
      "name": "Tarsal"
    },
    {
      "number": 281,
      "name": "Kirlia"
    },
    {
      "number": 282,
      "name": "Gardevoir"
    },
    {
      "number": 283,
      "name": "Arakdo"
    },
    {
      "number": 284,
      "name": "Maskadra"
    },
    {
      "number": 285,
      "name": "Balignon"
    },
    {
      "number": 286,
      "name": "Chapignon"
    },
    {
      "number": 287,
      "name": "Parecool"
    },
    {
      "number": 288,
      "name": "Vigoroth"
    },
    {
      "number": 289,
      "name": "Monaflèmit"
    },
    {
      "number": 290,
      "name": "Ningale"
    },
    {
      "number": 291,
      "name": "Ninjask"
    },
    {
      "number": 292,
      "name": "Munja"
    },
    {
      "number": 293,
      "name": "Chuchmur"
    },
    {
      "number": 294,
      "name": "Ramboum"
    },
    {
      "number": 295,
      "name": "Brouhabam"
    },
    {
      "number": 296,
      "name": "Makuhita"
    },
    {
      "number": 297,
      "name": "Hariyama"
    },
    {
      "number": 298,
      "name": "Azurill"
    },
    {
      "number": 299,
      "name": "Tarinor"
    },
    {
      "number": 300,
      "name": "Skitty"
    },
    {
      "number": 301,
      "name": "Delcatty"
    },
    {
      "number": 302,
      "name": "Ténéfix"
    },
    {
      "number": 303,
      "name": "Mysdibule"
    },
    {
      "number": 304,
      "name": "Galekid"
    },
    {
      "number": 305,
      "name": "Galegon"
    },
    {
      "number": 306,
      "name": "Galeking"
    },
    {
      "number": 307,
      "name": "Méditikka"
    },
    {
      "number": 308,
      "name": "Charmina"
    },
    {
      "number": 309,
      "name": "Dynavolt"
    },
    {
      "number": 310,
      "name": "Élecsprint"
    },
    {
      "number": 311,
      "name": "Posipi"
    },
    {
      "number": 312,
      "name": "Négapi"
    },
    {
      "number": 313,
      "name": "Muciole"
    },
    {
      "number": 314,
      "name": "Lumivole"
    },
    {
      "number": 315,
      "name": "Rosélia"
    },
    {
      "number": 316,
      "name": "Gloupti"
    },
    {
      "number": 317,
      "name": "Avaltout"
    },
    {
      "number": 318,
      "name": "Carvanha"
    },
    {
      "number": 319,
      "name": "Sharpedo"
    },
    {
      "number": 320,
      "name": "Wailmer"
    },
    {
      "number": 321,
      "name": "Wailord"
    },
    {
      "number": 322,
      "name": "Chamallot"
    },
    {
      "number": 323,
      "name": "Camérupt"
    },
    {
      "number": 324,
      "name": "Chartor"
    },
    {
      "number": 325,
      "name": "Spoink"
    },
    {
      "number": 326,
      "name": "Groret"
    },
    {
      "number": 327,
      "name": "Spinda"
    },
    {
      "number": 328,
      "name": "Kraknoix"
    },
    {
      "number": 329,
      "name": "Vibraninf"
    },
    {
      "number": 330,
      "name": "Libégon"
    },
    {
      "number": 331,
      "name": "Cacnea"
    },
    {
      "number": 332,
      "name": "Cacturne"
    },
    {
      "number": 333,
      "name": "Tylton"
    },
    {
      "number": 334,
      "name": "Altaria"
    },
    {
      "number": 335,
      "name": "Mangriff"
    },
    {
      "number": 336,
      "name": "Séviper"
    },
    {
      "number": 337,
      "name": "Séléroc"
    },
    {
      "number": 338,
      "name": "Solaroc"
    },
    {
      "number": 339,
      "name": "Barloche"
    },
    {
      "number": 340,
      "name": "Barbicha"
    },
    {
      "number": 341,
      "name": "Écrapince"
    },
    {
      "number": 342,
      "name": "Colhomard"
    },
    {
      "number": 343,
      "name": "Balbuto"
    },
    {
      "number": 344,
      "name": "Kaorine"
    },
    {
      "number": 345,
      "name": "Lilia"
    },
    {
      "number": 346,
      "name": "Vacilys"
    },
    {
      "number": 347,
      "name": "Anorith"
    },
    {
      "number": 348,
      "name": "Armaldo"
    },
    {
      "number": 349,
      "name": "Barpau"
    },
    {
      "number": 350,
      "name": "Milobellus"
    },
    {
      "number": 351,
      "name": "Morphéo"
    },
    {
      "number": 352,
      "name": "Kecleon"
    },
    {
      "number": 353,
      "name": "Polichombr"
    },
    {
      "number": 354,
      "name": "Branette"
    },
    {
      "number": 355,
      "name": "Skelénox"
    },
    {
      "number": 356,
      "name": "Téraclope"
    },
    {
      "number": 357,
      "name": "Tropius"
    },
    {
      "number": 358,
      "name": "Éoko"
    },
    {
      "number": 359,
      "name": "Absol"
    },
    {
      "number": 360,
      "name": "Okéoké"
    },
    {
      "number": 361,
      "name": "Stalgamin"
    },
    {
      "number": 362,
      "name": "Oniglali"
    },
    {
      "number": 363,
      "name": "Obalie"
    },
    {
      "number": 364,
      "name": "Phogleur"
    },
    {
      "number": 365,
      "name": "Kaimorse"
    },
    {
      "number": 366,
      "name": "Coquiperl"
    },
    {
      "number": 367,
      "name": "Serpang"
    },
    {
      "number": 368,
      "name": "Rosabyss"
    },
    {
      "number": 369,
      "name": "Relicanth"
    },
    {
      "number": 370,
      "name": "Lovdisc"
    },
    {
      "number": 371,
      "name": "Draby"
    },
    {
      "number": 372,
      "name": "Drackhaus"
    },
    {
      "number": 373,
      "name": "Drattak"
    },
    {
      "number": 374,
      "name": "Terhal"
    },
    {
      "number": 375,
      "name": "Métang"
    },
    {
      "number": 376,
      "name": "Métalosse"
    },
    {
      "number": 377,
      "name": "Regirock"
    },
    {
      "number": 378,
      "name": "Regice"
    },
    {
      "number": 379,
      "name": "Registeel"
    },
    {
      "number": 380,
      "name": "Latias"
    },
    {
      "number": 381,
      "name": "Latios"
    },
    {
      "number": 382,
      "name": "Kyogre"
    },
    {
      "number": 383,
      "name": "Groudon"
    },
    {
      "number": 384,
      "name": "Rayquaza"
    },
    {
      "number": 385,
      "name": "Jirachi"
    },
    {
      "number": 386,
      "name": "Deoxys"
    },
    {
      "number": 387,
      "name": "Tortipouss"
    },
    {
      "number": 388,
      "name": "Boskara"
    },
    {
      "number": 389,
      "name": "Torterra"
    },
    {
      "number": 390,
      "name": "Ouisticram"
    },
    {
      "number": 391,
      "name": "Chimpenfeu"
    },
    {
      "number": 392,
      "name": "Simiabraz"
    },
    {
      "number": 393,
      "name": "Tiplouf"
    },
    {
      "number": 394,
      "name": "Prinplouf"
    },
    {
      "number": 395,
      "name": "Pingoléon"
    },
    {
      "number": 396,
      "name": "Étourmi"
    },
    {
      "number": 397,
      "name": "Étourvol"
    },
    {
      "number": 398,
      "name": "Étouraptor"
    },
    {
      "number": 399,
      "name": "Keunotor"
    },
    {
      "number": 400,
      "name": "Castorno"
    },
    {
      "number": 401,
      "name": "Crikzik"
    },
    {
      "number": 402,
      "name": "Mélokrik"
    },
    {
      "number": 403,
      "name": "Lixy"
    },
    {
      "number": 404,
      "name": "Luxio"
    },
    {
      "number": 405,
      "name": "Luxray"
    },
    {
      "number": 406,
      "name": "Rozbouton"
    },
    {
      "number": 407,
      "name": "Roserade"
    },
    {
      "number": 408,
      "name": "Kranidos"
    },
    {
      "number": 409,
      "name": "Charkos"
    },
    {
      "number": 410,
      "name": "Dinoclier"
    },
    {
      "number": 411,
      "name": "Bastiodon"
    },
    {
      "number": 412,
      "name": "Cheniti"
    },
    {
      "number": 413,
      "name": "Cheniselle"
    },
    {
      "number": 414,
      "name": "Papilord"
    },
    {
      "number": 415,
      "name": "Apitrini"
    },
    {
      "number": 416,
      "name": "Apireine"
    },
    {
      "number": 417,
      "name": "Pachirisu"
    },
    {
      "number": 418,
      "name": "Mustébouée"
    },
    {
      "number": 419,
      "name": "Mustéflott"
    },
    {
      "number": 420,
      "name": "Ceribou"
    },
    {
      "number": 421,
      "name": "Ceriflor"
    },
    {
      "number": 422,
      "name": "Sancoki"
    },
    {
      "number": 423,
      "name": "Tritosor"
    },
    {
      "number": 424,
      "name": "Capidextre"
    },
    {
      "number": 425,
      "name": "Baudrive"
    },
    {
      "number": 426,
      "name": "Grodrive"
    },
    {
      "number": 427,
      "name": "Laporeille"
    },
    {
      "number": 428,
      "name": "Lockpin"
    },
    {
      "number": 429,
      "name": "Magirêve"
    },
    {
      "number": 430,
      "name": "Corboss"
    },
    {
      "number": 431,
      "name": "Chaglam"
    },
    {
      "number": 432,
      "name": "Chaffreux"
    },
    {
      "number": 433,
      "name": "Korillon"
    },
    {
      "number": 434,
      "name": "Moufouette"
    },
    {
      "number": 435,
      "name": "Moufflair"
    },
    {
      "number": 436,
      "name": "Archéomire"
    },
    {
      "number": 437,
      "name": "Archéodong"
    },
    {
      "number": 438,
      "name": "Manzaï"
    },
    {
      "number": 439,
      "name": "Mime Jr."
    },
    {
      "number": 440,
      "name": "Ptiravi"
    },
    {
      "number": 441,
      "name": "Pijako"
    },
    {
      "number": 442,
      "name": "Spiritomb"
    },
    {
      "number": 443,
      "name": "Griknot"
    },
    {
      "number": 444,
      "name": "Carmache"
    },
    {
      "number": 445,
      "name": "Carchacrok"
    },
    {
      "number": 446,
      "name": "Goinfrex"
    },
    {
      "number": 447,
      "name": "Riolu"
    },
    {
      "number": 448,
      "name": "Lucario"
    },
    {
      "number": 449,
      "name": "Hippopotas"
    },
    {
      "number": 450,
      "name": "Hippodocus"
    },
    {
      "number": 451,
      "name": "Rapion"
    },
    {
      "number": 452,
      "name": "Drascore"
    },
    {
      "number": 453,
      "name": "Cradopaud"
    },
    {
      "number": 454,
      "name": "Coatox"
    },
    {
      "number": 455,
      "name": "Vortente"
    },
    {
      "number": 456,
      "name": "Écayon"
    },
    {
      "number": 457,
      "name": "Luminéon"
    },
    {
      "number": 458,
      "name": "Babimanta"
    },
    {
      "number": 459,
      "name": "Blizzi"
    },
    {
      "number": 460,
      "name": "Blizzaroi"
    },
    {
      "number": 461,
      "name": "Dimoret"
    },
    {
      "number": 462,
      "name": "Magnézone"
    },
    {
      "number": 463,
      "name": "Coudlangue"
    },
    {
      "number": 464,
      "name": "Rhinastoc"
    },
    {
      "number": 465,
      "name": "Bouldeneu"
    },
    {
      "number": 466,
      "name": "Élekable"
    },
    {
      "number": 467,
      "name": "Maganon"
    },
    {
      "number": 468,
      "name": "Togekiss"
    },
    {
      "number": 469,
      "name": "Yanméga"
    },
    {
      "number": 470,
      "name": "Phyllali"
    },
    {
      "number": 471,
      "name": "Givrali"
    },
    {
      "number": 472,
      "name": "Scorvol"
    },
    {
      "number": 473,
      "name": "Mammochon"
    },
    {
      "number": 474,
      "name": "Porygon-Z"
    },
    {
      "number": 475,
      "name": "Gallame"
    },
    {
      "number": 476,
      "name": "Tarinorme"
    },
    {
      "number": 477,
      "name": "Noctunoir"
    },
    {
      "number": 478,
      "name": "Momartik"
    },
    {
      "number": 479,
      "name": "Motisma"
    },
    {
      "number": 480,
      "name": "Créhelf"
    },
    {
      "number": 481,
      "name": "Créfollet"
    },
    {
      "number": 482,
      "name": "Créfadet"
    },
    {
      "number": 483,
      "name": "Dialga"
    },
    {
      "number": 484,
      "name": "Palkia"
    },
    {
      "number": 485,
      "name": "Heatran"
    },
    {
      "number": 486,
      "name": "Regigigas"
    },
    {
      "number": 487,
      "name": "Giratina"
    },
    {
      "number": 488,
      "name": "Cresselia"
    },
    {
      "number": 489,
      "name": "Phione"
    },
    {
      "number": 490,
      "name": "Manaphy"
    },
    {
      "number": 491,
      "name": "Darkrai"
    },
    {
      "number": 492,
      "name": "Shaymin"
    },
    {
      "number": 493,
      "name": "Arceus"
    },
    {
      "number": 494,
      "name": "Victini"
    },
    {
      "number": 495,
      "name": "Vipélierre"
    },
    {
      "number": 496,
      "name": "Lianaja"
    },
    {
      "number": 497,
      "name": "Majaspic"
    },
    {
      "number": 498,
      "name": "Gruikui"
    },
    {
      "number": 499,
      "name": "Grotichon"
    },
    {
      "number": 500,
      "name": "Roitiflam"
    },
    {
      "number": 501,
      "name": "Moustillon"
    },
    {
      "number": 502,
      "name": "Mateloutre"
    },
    {
      "number": 503,
      "name": "Clamiral"
    },
    {
      "number": 504,
      "name": "Ratentif"
    },
    {
      "number": 505,
      "name": "Miradar"
    },
    {
      "number": 506,
      "name": "Ponchiot"
    },
    {
      "number": 507,
      "name": "Ponchien"
    },
    {
      "number": 508,
      "name": "Mastouffe"
    },
    {
      "number": 509,
      "name": "Chacripan"
    },
    {
      "number": 510,
      "name": "Léopardus"
    },
    {
      "number": 511,
      "name": "Feuillajou"
    },
    {
      "number": 512,
      "name": "Feuiloutan"
    },
    {
      "number": 513,
      "name": "Flamajou"
    },
    {
      "number": 514,
      "name": "Flamoutan"
    },
    {
      "number": 515,
      "name": "Flotajou"
    },
    {
      "number": 516,
      "name": "Flotoutan"
    },
    {
      "number": 517,
      "name": "Munna"
    },
    {
      "number": 518,
      "name": "Mushana"
    },
    {
      "number": 519,
      "name": "Poichigeon"
    },
    {
      "number": 520,
      "name": "Colombeau"
    },
    {
      "number": 521,
      "name": "Déflaisan"
    },
    {
      "number": 522,
      "name": "Zébibron"
    },
    {
      "number": 523,
      "name": "Zéblitz"
    },
    {
      "number": 524,
      "name": "Nodulithe"
    },
    {
      "number": 525,
      "name": "Géolithe"
    },
    {
      "number": 526,
      "name": "Gigalithe"
    },
    {
      "number": 527,
      "name": "Chovsourir"
    },
    {
      "number": 528,
      "name": "Rhinolove"
    },
    {
      "number": 529,
      "name": "Rototaupe"
    },
    {
      "number": 530,
      "name": "Minotaupe"
    },
    {
      "number": 531,
      "name": "Nanméouïe"
    },
    {
      "number": 532,
      "name": "Charpenti"
    },
    {
      "number": 533,
      "name": "Ouvrifier"
    },
    {
      "number": 534,
      "name": "Bétochef"
    },
    {
      "number": 535,
      "name": "Tritonde"
    },
    {
      "number": 536,
      "name": "Batracné"
    },
    {
      "number": 537,
      "name": "Crapustule"
    },
    {
      "number": 538,
      "name": "Judokrak"
    },
    {
      "number": 539,
      "name": "Karaclée"
    },
    {
      "number": 540,
      "name": "Larveyette"
    },
    {
      "number": 541,
      "name": "Couverdure"
    },
    {
      "number": 542,
      "name": "Manternel"
    },
    {
      "number": 543,
      "name": "Venipatte"
    },
    {
      "number": 544,
      "name": "Scobolide"
    },
    {
      "number": 545,
      "name": "Brutapode"
    },
    {
      "number": 546,
      "name": "Doudouvet"
    },
    {
      "number": 547,
      "name": "Farfaduvet"
    },
    {
      "number": 548,
      "name": "Chlorobule"
    },
    {
      "number": 549,
      "name": "Fragilady"
    },
    {
      "number": 550,
      "name": "Bargantua"
    },
    {
      "number": 551,
      "name": "Mascaïman"
    },
    {
      "number": 552,
      "name": "Escroco"
    },
    {
      "number": 553,
      "name": "Crocorible"
    },
    {
      "number": 554,
      "name": "Darumarond"
    },
    {
      "number": 555,
      "name": "Darumacho"
    },
    {
      "number": 556,
      "name": "Maracachi"
    },
    {
      "number": 557,
      "name": "Crabicoque"
    },
    {
      "number": 558,
      "name": "Crabaraque"
    },
    {
      "number": 559,
      "name": "Baggiguane"
    },
    {
      "number": 560,
      "name": "Baggaïd"
    },
    {
      "number": 561,
      "name": "Cryptéro"
    },
    {
      "number": 562,
      "name": "Tutafeh"
    },
    {
      "number": 563,
      "name": "Tutankafer"
    },
    {
      "number": 564,
      "name": "Carapagos"
    },
    {
      "number": 565,
      "name": "Mégapagos"
    },
    {
      "number": 566,
      "name": "Arkéapti"
    },
    {
      "number": 567,
      "name": "Aéroptéryx"
    },
    {
      "number": 568,
      "name": "Miamiasme"
    },
    {
      "number": 569,
      "name": "Miasmax"
    },
    {
      "number": 570,
      "name": "Zorua"
    },
    {
      "number": 571,
      "name": "Zoroark"
    },
    {
      "number": 572,
      "name": "Chinchidou"
    },
    {
      "number": 573,
      "name": "Pashmilla"
    },
    {
      "number": 574,
      "name": "Scrutella"
    },
    {
      "number": 575,
      "name": "Mesmérella"
    },
    {
      "number": 576,
      "name": "Sidérella"
    },
    {
      "number": 577,
      "name": "Nucléos"
    },
    {
      "number": 578,
      "name": "Méios"
    },
    {
      "number": 579,
      "name": "Symbios"
    },
    {
      "number": 580,
      "name": "Couaneton"
    },
    {
      "number": 581,
      "name": "Lakmécygne"
    },
    {
      "number": 582,
      "name": "Sorbébé"
    },
    {
      "number": 583,
      "name": "Sorboul"
    },
    {
      "number": 584,
      "name": "Sorbouboul"
    },
    {
      "number": 585,
      "name": "Vivaldaim"
    },
    {
      "number": 586,
      "name": "Haydaim"
    },
    {
      "number": 587,
      "name": "Emolga"
    },
    {
      "number": 588,
      "name": "Carabing"
    },
    {
      "number": 589,
      "name": "Lançargot"
    },
    {
      "number": 590,
      "name": "Trompignon"
    },
    {
      "number": 591,
      "name": "Gaulet"
    },
    {
      "number": 592,
      "name": "Viskuse"
    },
    {
      "number": 593,
      "name": "Moyade"
    },
    {
      "number": 594,
      "name": "Mamanbo"
    },
    {
      "number": 595,
      "name": "Statitik"
    },
    {
      "number": 596,
      "name": "Mygavolt"
    },
    {
      "number": 597,
      "name": "Grindur"
    },
    {
      "number": 598,
      "name": "Noacier"
    },
    {
      "number": 599,
      "name": "Tic"
    },
    {
      "number": 600,
      "name": "Clic"
    },
    {
      "number": 601,
      "name": "Cliticlic"
    },
    {
      "number": 602,
      "name": "Anchwatt"
    },
    {
      "number": 603,
      "name": "Lampéroie"
    },
    {
      "number": 604,
      "name": "Ohmassacre"
    },
    {
      "number": 605,
      "name": "Lewsor"
    },
    {
      "number": 606,
      "name": "Neitram"
    },
    {
      "number": 607,
      "name": "Funécire"
    },
    {
      "number": 608,
      "name": "Mélancolux"
    },
    {
      "number": 609,
      "name": "Lugulabre"
    },
    {
      "number": 610,
      "name": "Coupenotte"
    },
    {
      "number": 611,
      "name": "Incisache"
    },
    {
      "number": 612,
      "name": "Tranchodon"
    },
    {
      "number": 613,
      "name": "Polarhume"
    },
    {
      "number": 614,
      "name": "Polagriffe"
    },
    {
      "number": 615,
      "name": "Hexagel"
    },
    {
      "number": 616,
      "name": "Escargaume"
    },
    {
      "number": 617,
      "name": "Limaspeed"
    },
    {
      "number": 618,
      "name": "Limonde"
    },
    {
      "number": 619,
      "name": "Kungfouine"
    },
    {
      "number": 620,
      "name": "Shaofouine"
    },
    {
      "number": 621,
      "name": "Drakkarmin"
    },
    {
      "number": 622,
      "name": "Gringolem"
    },
    {
      "number": 623,
      "name": "Golemastoc"
    },
    {
      "number": 624,
      "name": "Scalpion"
    },
    {
      "number": 625,
      "name": "Scalproie"
    },
    {
      "number": 626,
      "name": "Frison"
    },
    {
      "number": 627,
      "name": "Furaiglon"
    },
    {
      "number": 628,
      "name": "Gueriaigle"
    },
    {
      "number": 629,
      "name": "Vostourno"
    },
    {
      "number": 630,
      "name": "Vaututrice"
    },
    {
      "number": 631,
      "name": "Aflamanoir"
    },
    {
      "number": 632,
      "name": "Fermite"
    },
    {
      "number": 633,
      "name": "Solochi"
    },
    {
      "number": 634,
      "name": "Diamat"
    },
    {
      "number": 635,
      "name": "Trioxhydre"
    },
    {
      "number": 636,
      "name": "Pyronille"
    },
    {
      "number": 637,
      "name": "Pyrax"
    },
    {
      "number": 638,
      "name": "Cobaltium"
    },
    {
      "number": 639,
      "name": "Terrakium"
    },
    {
      "number": 640,
      "name": "Viridium"
    },
    {
      "number": 641,
      "name": "Boréas"
    },
    {
      "number": 642,
      "name": "Fulguris"
    },
    {
      "number": 643,
      "name": "Reshiram"
    },
    {
      "number": 644,
      "name": "Zekrom"
    },
    {
      "number": 645,
      "name": "Démétéros"
    },
    {
      "number": 646,
      "name": "Kyurem"
    },
    {
      "number": 647,
      "name": "Keldeo"
    },
    {
      "number": 648,
      "name": "Meloetta"
    },
    {
      "number": 649,
      "name": "Genesect"
    },
    {
      "number": 650,
      "name": "Marisson"
    },
    {
      "number": 651,
      "name": "Boguérisse"
    },
    {
      "number": 652,
      "name": "Blindépique"
    },
    {
      "number": 653,
      "name": "Feunnec"
    },
    {
      "number": 654,
      "name": "Roussil"
    },
    {
      "number": 655,
      "name": "Goupelin"
    },
    {
      "number": 656,
      "name": "Grenousse"
    },
    {
      "number": 657,
      "name": "Croâporal"
    },
    {
      "number": 658,
      "name": "Amphinobi"
    },
    {
      "number": 659,
      "name": "Sapereau"
    },
    {
      "number": 660,
      "name": "Excavarenne"
    },
    {
      "number": 661,
      "name": "Passerouge"
    },
    {
      "number": 662,
      "name": "Braisillon"
    },
    {
      "number": 663,
      "name": "Flambusard"
    },
    {
      "number": 664,
      "name": "Lépidonille"
    },
    {
      "number": 665,
      "name": "Pérégrain"
    },
    {
      "number": 666,
      "name": "Prismillon"
    },
    {
      "number": 667,
      "name": "Hélionceau"
    },
    {
      "number": 668,
      "name": "Némélios"
    },
    {
      "number": 669,
      "name": "Flabébé"
    },
    {
      "number": 670,
      "name": "Floette"
    },
    {
      "number": 671,
      "name": "Florges"
    },
    {
      "number": 672,
      "name": "Cabriolaine"
    },
    {
      "number": 673,
      "name": "Chevroum"
    },
    {
      "number": 674,
      "name": "Pandespiègle"
    },
    {
      "number": 675,
      "name": "Pandarbare"
    },
    {
      "number": 676,
      "name": "Couafarel"
    },
    {
      "number": 677,
      "name": "Psystigri"
    },
    {
      "number": 678,
      "name": "Mistigrix"
    },
    {
      "number": 679,
      "name": "Monorpale"
    },
    {
      "number": 680,
      "name": "Dimoclès"
    },
    {
      "number": 681,
      "name": "Exagide"
    },
    {
      "number": 682,
      "name": "Fluvetin"
    },
    {
      "number": 683,
      "name": "Cocotine"
    },
    {
      "number": 684,
      "name": "Sucroquin"
    },
    {
      "number": 685,
      "name": "Cupcanaille"
    },
    {
      "number": 686,
      "name": "Sepiatop"
    },
    {
      "number": 687,
      "name": "Sepiatroce"
    },
    {
      "number": 688,
      "name": "Opermine"
    },
    {
      "number": 689,
      "name": "Golgopathe"
    },
    {
      "number": 690,
      "name": "Venalgue"
    },
    {
      "number": 691,
      "name": "Kravarech"
    },
    {
      "number": 692,
      "name": "Flingouste"
    },
    {
      "number": 693,
      "name": "Gamblast"
    },
    {
      "number": 694,
      "name": "Galvaran"
    },
    {
      "number": 695,
      "name": "Iguolta"
    },
    {
      "number": 696,
      "name": "Ptyranidur"
    },
    {
      "number": 697,
      "name": "Rexillius"
    },
    {
      "number": 698,
      "name": "Amagara"
    },
    {
      "number": 699,
      "name": "Dragmara"
    },
    {
      "number": 700,
      "name": "Nymphali"
    },
    {
      "number": 701,
      "name": "Brutalibré"
    },
    {
      "number": 702,
      "name": "Dedenne"
    },
    {
      "number": 703,
      "name": "Strassie"
    },
    {
      "number": 704,
      "name": "Mucuscule"
    },
    {
      "number": 705,
      "name": "Colimucus"
    },
    {
      "number": 706,
      "name": "Muplodocus"
    },
    {
      "number": 707,
      "name": "Trousselin"
    },
    {
      "number": 708,
      "name": "Brocélôme"
    },
    {
      "number": 709,
      "name": "Desséliande"
    },
    {
      "number": 710,
      "name": "Pitrouille"
    },
    {
      "number": 711,
      "name": "Banshitrouye"
    },
    {
      "number": 712,
      "name": "Grelaçon"
    },
    {
      "number": 713,
      "name": "Séracrawl"
    },
    {
      "number": 714,
      "name": "Sonistrelle"
    },
    {
      "number": 715,
      "name": "Bruyverne"
    },
    {
      "number": 716,
      "name": "Xerneas"
    },
    {
      "number": 717,
      "name": "Yveltal"
    },
    {
      "number": 718,
      "name": "Zygarde"
    },
    {
      "number": 719,
      "name": "Diancie"
    },
    {
      "number": 720,
      "name": "Hoopa"
    },
    {
      "number": 721,
      "name": "Volcanion"
    },
    {
      "number": 722,
      "name": "Brindibou"
    },
    {
      "number": 723,
      "name": "Efflèche"
    },
    {
      "number": 724,
      "name": "Archéduc"
    },
    {
      "number": 725,
      "name": "Flamiaou"
    },
    {
      "number": 726,
      "name": "Matoufeu"
    },
    {
      "number": 727,
      "name": "Félinferno"
    },
    {
      "number": 728,
      "name": "Otaquin"
    },
    {
      "number": 729,
      "name": "Otarlette"
    },
    {
      "number": 730,
      "name": "Oratoria"
    },
    {
      "number": 731,
      "name": "Picassaut"
    },
    {
      "number": 732,
      "name": "Piclairon"
    },
    {
      "number": 733,
      "name": "Bazoucan"
    },
    {
      "number": 734,
      "name": "Manglouton"
    },
    {
      "number": 735,
      "name": "Argouste"
    },
    {
      "number": 736,
      "name": "Larvibule"
    },
    {
      "number": 737,
      "name": "Chrysapile"
    },
    {
      "number": 738,
      "name": "Lucanon"
    },
    {
      "number": 739,
      "name": "Crabagarre"
    },
    {
      "number": 740,
      "name": "Crabominable"
    },
    {
      "number": 741,
      "name": "Plumeline"
    },
    {
      "number": 742,
      "name": "Bombydou"
    },
    {
      "number": 743,
      "name": "Rubombelle"
    },
    {
      "number": 744,
      "name": "Rocabot"
    },
    {
      "number": 745,
      "name": "Lougaroc"
    },
    {
      "number": 746,
      "name": "Froussardine"
    },
    {
      "number": 747,
      "name": "Vorastérie"
    },
    {
      "number": 748,
      "name": "Prédastérie"
    },
    {
      "number": 749,
      "name": "Tiboudet"
    },
    {
      "number": 750,
      "name": "Bourrinos"
    },
    {
      "number": 751,
      "name": "Araqua"
    },
    {
      "number": 752,
      "name": "Tarenbulle"
    },
    {
      "number": 753,
      "name": "Mimantis"
    },
    {
      "number": 754,
      "name": "Floramantis"
    },
    {
      "number": 755,
      "name": "Spododo"
    },
    {
      "number": 756,
      "name": "Lampignon"
    },
    {
      "number": 757,
      "name": "Tritox"
    },
    {
      "number": 758,
      "name": "Malamandre"
    },
    {
      "number": 759,
      "name": "Nounourson"
    },
    {
      "number": 760,
      "name": "Chelours"
    },
    {
      "number": 761,
      "name": "Croquine"
    },
    {
      "number": 762,
      "name": "Candine"
    },
    {
      "number": 763,
      "name": "Sucreine"
    },
    {
      "number": 764,
      "name": "Guérilande"
    },
    {
      "number": 765,
      "name": "Gouroutan"
    },
    {
      "number": 766,
      "name": "Quartermac"
    },
    {
      "number": 767,
      "name": "Sovkipou"
    },
    {
      "number": 768,
      "name": "Sarmuraï"
    },
    {
      "number": 769,
      "name": "Bacabouh"
    },
    {
      "number": 770,
      "name": "Trépassable"
    },
    {
      "number": 771,
      "name": "Concombaffe"
    },
    {
      "number": 772,
      "name": "Type:0"
    },
    {
      "number": 773,
      "name": "Silvallié"
    },
    {
      "number": 774,
      "name": "Météno"
    },
    {
      "number": 775,
      "name": "Dodoala"
    },
    {
      "number": 776,
      "name": "Boumata"
    },
    {
      "number": 777,
      "name": "Togedemaru"
    },
    {
      "number": 778,
      "name": "Mimiqui"
    },
    {
      "number": 779,
      "name": "Denticrisse"
    },
    {
      "number": 780,
      "name": "Draïeul"
    },
    {
      "number": 781,
      "name": "Sinistrail"
    },
    {
      "number": 782,
      "name": "Bébécaille"
    },
    {
      "number": 783,
      "name": "Écaïd"
    },
    {
      "number": 784,
      "name": "Ékaïser"
    },
    {
      "number": 785,
      "name": "Tokorico"
    },
    {
      "number": 786,
      "name": "Tokopiyon"
    },
    {
      "number": 787,
      "name": "Tokotoro"
    },
    {
      "number": 788,
      "name": "Tokopisco"
    },
    {
      "number": 789,
      "name": "Cosmog"
    },
    {
      "number": 790,
      "name": "Cosmovum"
    },
    {
      "number": 791,
      "name": "Solgaleo"
    },
    {
      "number": 792,
      "name": "Lunala"
    },
    {
      "number": 793,
      "name": "Zéroïd"
    },
    {
      "number": 794,
      "name": "Mouscoto"
    },
    {
      "number": 795,
      "name": "Cancrelove"
    },
    {
      "number": 796,
      "name": "Câblifère"
    },
    {
      "number": 797,
      "name": "Bamboiselle"
    },
    {
      "number": 798,
      "name": "Katagami"
    },
    {
      "number": 799,
      "name": "Engloutyran"
    },
    {
      "number": 800,
      "name": "Necrozma"
    },
    {
      "number": 801,
      "name": "Magearna"
    },
    {
      "number": 802,
      "name": "Marshadow"
    }
  ]
}